xlogit_extensions/__init__.py
xlogit_extensions/_choice_model.py
xlogit_extensions/_device.py
xlogit_extensions/boxcox_functions.py
xlogit_extensions/latent_class_model.py
xlogit_extensions/latent_class_model_mixed.py
xlogit_extensions/mixed_logit.py
xlogit_extensions/multinomial_logit.py
xlogit_extensions-0.0.4.dist-info/LICENSE
xlogit_extensions-0.0.4.dist-info/METADATA
xlogit_extensions-0.0.4.dist-info/WHEEL
xlogit_extensions-0.0.4.dist-info/top_level.txt
xlogit_extensions-0.0.4.dist-info/RECORD
