Metadata-Version: 2.1
Name: xlogit-extensions
Version: 0.0.4
Summary: Extensions for a Python package for                               GPU-accelerated estimation of mixed logit models.
Home-page: https://github.com/RyanJafefKelly/xlogit_extensions
Author: Ryan Kelly
Author-email: ryan@kiiii.com
License: MIT
Platform: UNKNOWN
Requires-Python: >=3.5
Requires-Dist: numpy (>=1.13.1)
Requires-Dist: scipy (>=1.0.0)
